geometrout/__init__.py
geometrout/_version.py
geometrout/maths.py
geometrout/pointcloud.py
geometrout/primitive.py
geometrout/transform.py
geometrout-0.1.3.dist-info/LICENSE
geometrout-0.1.3.dist-info/METADATA
geometrout-0.1.3.dist-info/WHEEL
geometrout-0.1.3.dist-info/top_level.txt
geometrout-0.1.3.dist-info/RECORD
