Metadata-Version: 2.1
Name: geometrout
Version: 0.1.3
Summary: A collection of geometric methods and concepts tailored to machine learning for robotics
License: MIT
Requires-Python: >=3.7
License-File: LICENSE
Requires-Dist: numpy
Requires-Dist: numba >=0.56.4
